<?xml version="1.0" encoding="utf-8"?><toc><breadcrumbs><li><a href="0133dca1-ad9f-ff93-4e93-324e7df2c303.htm">Docs</a></li><li><a href="0133dca1-ad9f-ff93-4e93-324e7df2c303.htm">Sensor<wbr />Data<wbr />Segmentation</a></li><li><a href="844f865e-1878-fe16-b748-b669d2277687.htm">Data<wbr />Graph</a></li></breadcrumbs><tocItems><li><a id="b1f0ceaa-7515-0702-2441-545216f5a1e6" href="b1f0ceaa-7515-0702-2441-545216f5a1e6.htm">Constructor</a></li><li><a id="dc223616-b6fc-1a62-aea0-514a91578caf" class="has-submenu" href="dc223616-b6fc-1a62-aea0-514a91578caf.htm"><span data-tocFile="../toc/IDBBA.xml" class="icon toggle" onclick="ToggleExpandCollapse(this); return false;"><i class="fa fa-angle-right"> </i></span>Properties</a><ul class="toc-menu is-hidden"> </ul></li><li><a id="d29d79ce-3e29-d5e4-0bb3-c4821715e7ac" class="has-submenu" href="d29d79ce-3e29-d5e4-0bb3-c4821715e7ac.htm"><span data-tocFile="../toc/IDCBA.xml" class="icon toggle" onclick="ToggleExpandCollapse(this); return false;"><i class="fa fa-angle-right"> </i></span>Methods</a><ul class="toc-menu is-hidden"> </ul></li><li><a id="9fc7d62e-9808-393b-7bf8-d953e37cd59c" href="9fc7d62e-9808-393b-7bf8-d953e37cd59c.htm">Events</a></li><li><a id="e3fa2d0a-f4cd-4bbb-367e-d3d0feac15d1" class="has-submenu" href="e3fa2d0a-f4cd-4bbb-367e-d3d0feac15d1.htm"><span data-tocFile="../toc/IDEBA.xml" class="icon toggle" onclick="ToggleExpandCollapse(this); return false;"><i class="fa fa-angle-right"> </i></span>Operators</a><ul class="toc-menu is-hidden"> </ul></li><li><a id="1ee403ba-8614-fb88-6560-c229512ffb60" class="has-submenu" href="1ee403ba-8614-fb88-6560-c229512ffb60.htm"><span data-tocFile="../toc/IDFBA.xml" class="icon toggle" onclick="ToggleExpandCollapse(this); return false;"><i class="fa fa-angle-right"> </i></span>Fields</a><ul class="toc-menu is-hidden"> </ul></li></tocItems></toc>